README.rst
setup.py
django_supertools.egg-info/PKG-INFO
django_supertools.egg-info/SOURCES.txt
django_supertools.egg-info/dependency_links.txt
django_supertools.egg-info/requires.txt
django_supertools.egg-info/top_level.txt
supertools/__init__.py
supertools/dates.py
supertools/http.py
supertools/json.py
supertools/middlewate/__init__.py
supertools/middlewate/merge_data.py
supertools/views/__init__.py
supertools/views/base.py
supertools/views/menu.py