Metadata-Version: 1.1
Name: django-supertools
Version: 0.2
Summary: Generic tools for django apps.
Home-page: https://github.com/kaleidos/django-supertools
Author: Jesús Espino García & Andrey Antukh
Author-email: jespinog@gmail.com, niwi@niwi.be
License: BSD
Keywords: django
Platform: UNKNOWN
Classifier: Programming Language :: Python
Classifier: Development Status :: 5 - Production/Stable
Classifier: Intended Audience :: Developers
Classifier: License :: OSI Approved :: BSD License
Classifier: Operating System :: OS Independent
Classifier: Programming Language :: Python
Classifier: Topic :: Internet :: WWW/HTTP
Classifier: Framework :: Django
Classifier: Programming Language :: Python
Classifier: Programming Language :: Python :: 2
Classifier: Programming Language :: Python :: 2.7
Classifier: Programming Language :: Python :: 3
Classifier: Programming Language :: Python :: 3.2
Classifier: Programming Language :: Python :: 3.3
